essen_BJS/__init__.py
essen_BJS/add.py
essen_BJS/ceil.py
essen_BJS/device_name.py
essen_BJS/div.py
essen_BJS/floor.py
essen_BJS/flr.py
essen_BJS/get_system.py
essen_BJS/hide_file.py
essen_BJS/logged_username.py
essen_BJS/main.py
essen_BJS/mod.py
essen_BJS/mult.py
essen_BJS/pow.py
essen_BJS/round.py
essen_BJS/spec_err.py
essen_BJS/sub.py
essen_bjs-0.2.1.dist-info/METADATA
essen_bjs-0.2.1.dist-info/WHEEL
essen_bjs-0.2.1.dist-info/RECORD
